{
  "deal_id": 16076,
  "title": "crystal-sound.com",
  "stage": "C10:EXECUTING",
  "opportunity": "0.00",
  "company_id": "24438",
  "contact_id": "35816",
  "site": "",
  "company_revenue": "162",
  "services_note": [
    "AEO: "
  ],
  "sfera_id": "9492",
  "brief": {
    "ФИО": "Анастасия",
    "Телефон": "+7 905 260-19-72",
    "Крайний срок для задачи на КП": "2026-06-09T03:00:00+03:00",
    "Целевой результат": "объяснил, что это история скорее про упоминание бренда, приняла",
    "Название компании": "Бренд - CrystalSound, ООО - Кристалл",
    "Адрес вашего сайта": "crystal-sound.com",
    "Приоритетные услуги или направления": "Основной продукт - радиогид, но в целом ",
    "Сильные стороны и отличия от конкурентов": "Российское производство, все инженеры здесь, могут настроить под ключ под конкретные задачи, закастомить, 2 года гарантии",
    "Запросы клиентов, которые отыгрываем": "понятно, что в первую очередь интересуют коммерческие по приоритетным напривлениям",
    "Конкуренты — кого вы считаете": "cromi.ru, radio-guide.ru и retekess.com.ru",
    "Страницы для продвижения": "Приоритеты - страницы услуг",
    "На чём сделан сайт": "Тильда",
    "Готовность к статьям на сторонних площадках": "есть",
    "Отраслевые и юридические ограничения": "-",
    "Срок и формат работы": "обозначал, что это постоянная работа, а первые микро-плоды могут быть видны месяца через 3",
    "Ориентир по бюджету": "называл 100-110"
  },
  "transcript": "Бриф crystal-sound.com\n======================\n\nСоздано с помощью: memoai.tech\nДата транскрипции: 09.06.2026 11:43\nДлительность: 00:39:19\nТеги: SEO, Диджитал, Маркетинг\nУчастники: Анастасия, Руководитель отдела маркетинга\n\nКраткое содержание\n------------------\nВ разговоре обсуждается текущая стратегия диджитал-маркетинга и SEO для сайта на платформе Тильда, включая вопросы по индексации в Яндексе и Google, а также возможное улучшение за счет ссылочной массы. Подчеркивается важность продвижения в Google и влияние рекламных кампаний на поведенческие факторы. Обсуждаются приоритетные продукты компании и возможности создания контента для блога. Рассматриваются потенциальные инвестиции в SEO и проблемы с нейроответами, влияющими на видимость в поиске.\n\nРасшифровка\n-----------\n\n[00:00] Анастасия: люблю периодически потом переслушивать какие-то моменты, фиксировать для себя. Запись включил. Демонстрацию сейчас тоже буду включать. Ну, и, соответственно, пробежимся по той инфе, которая у нас на руках есть. Я, Анастасия, буду чередовать какие-то вещи, которые буду показывать, с какими-то своими вопросами. Под конец вообще, скорее всего, я вас этими вопросами завалил.\n\n[00:24] Анастасия: В общем-то, Вопрос номер раз. Аркадий передал, что у вас есть команда, с кем вы работаете, да, вот в части диджитал-маркетинга, какие-то основные задачи закрываете, но хотелось бы понимать, какие. Мы говорим там только про SEO-шку или это полный цикл? Вот если чуть-чуть детальнее опишите, было бы полезно.\n\n[00:45] Руководитель отдела маркетинга: Слушайте, я руководитель отдела маркетинга. В моем подчинении, в общем-то, там пара человек, а остальное- это подрядчики. Подрядчик, как у нас, занимается рекламой контекстной на поиске SEO и промо-страницами с недавних пор. Буквально вот только запустили.\n\n[01:08] Руководитель отдела маркетинга: Ну, собственно, все. SEO мы не занимались особо, то есть только в рамках того, что можно сделать на сайте. Сайт на тильде.\n\n[01:19] Анастасия: Вот то, что сайт на тильде, да.\n\n[01:24] Руководитель отдела маркетинга: Сайт сейчас обновляется в процессе. То есть не глобально изменится, но кое-что в дизайне поменяется.\n\n[01:32] Анастасия: Так, а хочу уточнить вот то, что он на тильде, это незыблемая конструкция, если, допустим... Незыблемая, да. Вы переезжать не планируете, да, вы?\n\n[01:43] Руководитель отдела маркетинга: Нет.\n\n[01:45] Анастасия: Окей. Тут чуть-чуть мне взгрустнулось, на самом деле, не скрою. В общем, давайте пробежимся мы тогда по этому аудиту. Может быть, на будущее, скажем так, в любом случае эта инфа поможет. Тут вкратце история, почему по поводу тильда мне взгрустнулось. Мы в последнее время как-то совсем перестали с ней работать.\n\n[02:06] Анастасия: Коллегу точню на всякий случай, есть ли шансы, что мы все-таки попробуем взяться. Но, как сказал, в последнее время вообще плюнули немножко, потому что, ну, в общем-то, конкуренция ужесточается практически в любой сфере, в любой нише, а, соответственно, Tilda не все позволяет выполнить. И, грубо говоря, получается, что мы не полноценным SEO занимаемся, а какими-то потугами.\n\n[02:29] Анастасия: И, по большому счету, грубо говоря, те результаты, которые мы привыкли приносить, они значительно выше, чем те, которые можно принести за счет титля. Вот. В этом плане выбрали мы быть честными перед самим собой, скажем так. Но пробежимся, и на всякий случай все-таки у коллег уточню.\n\n[02:51] Анастасия: Вообще, у вас достаточно всегошно неплохие показатели, то есть если мы про индекс качества сайта от Яндекса, он составляет 270. Это... Абсолютная величина, скажем так, она на самом деле... ну, нельзя ее преобразовать в какие бы то ни было проценты, потому что никто не знает на самом деле, где максимум.\n\n[03:12] Анастасия: Ну, то есть 270 из скольких? Нет ответа на этот вопрос, но то есть там несколько тысяч может быть вполне, и мы с этим работали. Может, там потолок, я не знаю, в 10 тысяч, например. Такого я не видел на этом за свои годы в Диджитале, но год Самое главное- понимать, что 270 в целом- это адекватный, скажем так, показатель, учитывая, что у вас в целом в нише сайты не громадные сайты, да, там это не интернет-магазины, и, соответственно, там априори индекс качества не может там перелетать за 5 тысяч, я не знаю, я не знаю, за 5 тысяч, я не знаю, знаю.\n\n[03:48] Анастасия: Вот, соответственно, выглядит неплохо. Вот на этом подытожим. Что бросилось мне в глаза, на самом деле, у вас есть некоторый перекос с точки зрения индексации по количеству страниц в Яндексе и в Гугле. Рассказывает нам сервис то, что в Яндексе проиндексировано 320 страниц, в Гугле при этом 220.\n\n[04:11] Анастасия: Вот такая вот разница почти там в 30%. немного смущает. То есть в этом плане было бы правильно залезть в Search Console, в Webmaster и, соответственно, увидеть, в чем дело. Может быть такое, что Яндекс какой-то вообще просто технический мусор индексирует. Может быть такое, что Не знаю, Google не все у вас проиндексировал, и как-то он маловато вам доверяет.\n\n[04:39] Анастасия: Вторая версия мне больше нравится, потому что если вот уже на другую строчку посмотреть на ссылочное, там, где я курсором кручу, только один кружочек закрашен, и еще через несколько строчек я прыгну, вот здесь вот там количество ссылок, да, которые в вашем профиле присутствуют, но оно достаточно небольшое, а соответственно есть основания полагать, чтобы PageRank не очень высокий для Google.\n\n[05:04] Анастасия: Это, грубо говоря, такой показатель авторитетности, назовем это так, если очень простыми словами. Соответственно, может быть такое, что Google вообще не до конца вас индексирует, потому что просто еще не полноценно доверяет. Это как версия. То есть в теории со ссылочной массой, к примеру, можно было бы поработать.\n\n[05:26] Анастасия: Это не повредит, если ссылки адекватные и качественные, если закупать их плавно, а не самосвалом сразу. Ну, то есть если просто очень много закупать сразу, за это может санкция от поисковой системы прилететь. Это, в общем-то, тоже опасно. Теперь вопрос. На самом деле, у меня был по вот этому графику какой-то скачок.\n\n[05:48] Анастасия: прям неестественно выглядящий, и я хочу узнать, соотносятся ли вот эти цифры примерно с тем, что мы... что вы, в смысле, видите в метрике. Следите, скорее всего, за посещаемостью.\n\n[06:01] Руководитель отдела маркетинга: В апреле?\n\n[06:04] Анастасия: Угу. Ну, вот он показывает март 3,5, апрель 16,500.\n\n[06:10] Руководитель отдела маркетинга: Может, BTC у нас был запущен в апреле... Да, я не помню такого. 16500, давайте я посмотрю на сельдь. У нас же статистика на сельдь есть. Ну нет, у нас не было такой посещаемости в апреле.\n\n[06:52] Руководитель отдела маркетинга: Она примерно как в марте была, если смотреть количество сессий, количество сессий 5900, это сессии. Соответственно, ну там уровень заявок выше, чем в марте.\n\n[07:11] Анастасия: Интересно. Иногда, на самом деле, данные не совсем корректно парсятся этим сервисом, я поэтому как раз уточняю, то есть в этом плане...\n\n[07:19] Руководитель отдела маркетинга: Ну, и по просмотрам, да, сессии от просмотров, ну, примерно в два раза обычно отличаются. По просмотрам тоже на уровне марта данные.\n\n[07:31] Анастасия: Ну, в общем, понял. Здесь какой-то небольшой баг произошел. Это классика таких сервисов. То есть, опять же-таки, это уровень такого pre-pre-sale анализа. Здесь, понятное дело, если бы мы влезали там непосредственно поглубже в какие-то вещи, связанные с SEO, конечно, данные были бы более корректны.\n\n[07:52] Анастасия: Ну, а так, окей. Если такого скачка не было неестественного, то и замечательно. Может быть, на самом деле, какие-то роботные посещения, которые блочат метрики, которые не распознает сам Matilda, а при этом сервис, например, в теории может быть такое. Что еще можно рассказать?\n\n[08:15] Анастасия: Ну, про ссылочное я, собственно, рассказал. Здесь история такая, что с этим явно можно было бы поработать, учитывая, что, в общем-то, Ну, как сам сервис говорит, оно там в лучшем случае на треть вообще проработано. И, соответственно, под Google в первую очередь эти ссылки работают. Вот под Google можно было бы попробовать все-таки немного пошевелиться.\n\n[08:38] Анастасия: для того, чтобы чуть больше трафика все-таки собирать из поиска. Несмотря на то, что это тильда, да, вот как раз со ссылочной массой взаимодействовать вполне можно.\n\n[08:47] Руководитель отдела маркетинга: А можно еще чуть подробнее про ссылочную массу? Что это, если я представляю?\n\n[08:52] Анастасия: А, да-да-да. Вкратце, эта история такая, что если на каких-то ресурсах, которые являются авторитетными для поисковой системы, есть ссылки на ваш сайт, значит, вам можно больше доверять. читает, так, собственно, поисковики так считают. Вот, в общем-то, все просто. То есть есть определенные биржи, на которых собраны сайты, на которых можно закупить ссылки на ваш ресурс.\n\n[09:19] Анастасия: Соответственно, вот на подобного рода сервисах мы подыскиваем доноров так называемых. и размещаем как раз ссылки. Ну, то есть это форумы, это справочники, это какие-то там ваши ниши еще дополнительные, не знаю, агрегаторы, не агрегаторы, какие-то сайты с большими блоговыми разделами, куда можно написать статью, в которую можно интегрировать ссылку на нас.\n\n[09:43] Анастасия: Ну, вот, соответственно, это кусок, скажем так, SEO-шного продвижения.\n\n[09:47] Руководитель отдела маркетинга: И, как правило... Это реально по которым ходят люди или это чисто для системы ссылки?\n\n[09:53] Анастасия: Скорее, для системы в основном. Понятное дело, что кто-то может по ним переходить. Если мы говорим как раз про блоговые разделы, они, как правило, собирают достаточно много трафика, и, соответственно, какая-то кликабельность все-таки должна в статьях присутствовать. Но понятно, что это скорее капли в море. То есть в данном случае мы за счет ссылочной массы сильно не поднимем трафик.\n\n[10:18] Анастасия: Мы поднимем видимость в поисковых системах и уровень доверия. А вот за счет этого как раз, если вы там при ранжировании выше поднимаетесь, уже поднимется и трафик. То есть это, скорее, такая опосредованная история. Ну, еще, естественно, то, на что внимание стоит обратить, что явно есть зона роста, заключающаяся в том, что на данный момент, да, распознала система там около 207 ключевых запросов, по которым вас можно найти, при этом на первой странице вы находитесь по 83 из них.\n\n[10:48] Анастасия: Ну, то есть, грубо говоря, там почти в полтора раза можно... неправильно сказал, почти в два с половиной раза можно результат поднимать, даже почти в три. Соответственно, ну, зона роста видна. То, что можно поработать, в целом тоже видно. Вот, соответственно... А можно сразу вопрос на эту тему?\n\n[11:11] Руководитель отдела маркетинга: У нас не такой широкий набор продукции. Вообще, на самом деле, в общем-то, там, радиогид, аудиогид, синхронно-переводник. С парадином, это уже к ним. Откуда такой большой набор этих запросов? Это же не какой-то большой интернет-магазин все-таки.\n\n[11:32] Анастасия: Да, я согласен. Здесь история в том, что это не количество позиций, а количество запросов. То есть, грубо говоря, там одну и ту же позицию, не знаю, колбасу вязанка, могут вписать колбаса вязанка, могут вписать колбаса вареная, могут написать колбаса вареная цена, могут написать колбаса вареная купить, и все это разные запросы.\n\n[11:54] Руководитель отдела маркетинга: Да, я понимаю.\n\n[11:55] Анастасия: Каждой позиции там их можно подобрать по нескольку десятков. Вот, в общем-то, и все. То есть в этом плане Мы можем писать там радиогид, а можем писать оборудование для, я не знаю, прослушивания гид. Ну, и, соответственно, это всё разное.\n\n[12:15] Руководитель отдела маркетинга: Как это, дружит или не дружит с рекламой?\n\n[12:24] Анастасия: Как вам сказать? Нет такого, что не дружит. Ну, то есть вражды нет точно. Начнем с этого. Здесь нет, на самом деле, какой-то совсем прямой взаимосвязи между рекламой и SEO-шным продвижением. Но есть, опять же таки, опосредованно вот как с ссылками и трафиком. Здесь история заключающаяся в том, что, например, в большей степени Яндекс опирается на публические данные.\n\n[12:51] Анастасия: На как раз вот количество трафика, на одну минуту просмотра, на время, проведенное на сайте. соответственно, поведенческие данные, они начинают расти.\n\n[13:17] Анастасия: Соответственно, в данном случае Яндекс с точки зрения именно поисковой системы будет вас ранжировать повыше. То есть в этом плане реклама положительна.\n\n[13:26] Руководитель отдела маркетинга: Хорошо, а как с гублом быть? Он у вас... принимает этих пользователей для лыкс-ранжирования сайта или нет? На поведение пользователей Google смотрят или не особо?\n\n[13:44] Анастасия: Тоже смотрят, на самом деле, чуть-чуть в меньшей степени просто. Вот по опыту. То есть тут история какая. На самом деле факторы ранжирования, они почти одинаковые, что у Яндекса, что у Google. То есть они примерно одни и те же. только кто-то чуть сильнее опирается там на поведение пользователей, а Google, например, чуть больше на техничку и на вот это доверие на эти ссылки.\n\n[14:09] Анастасия: Но точно так же среди прочего, да, при прочих равных, если там поведенческие данные хорошие, естественно, это тоже положительно влияет.\n\n[14:20] Руководитель отдела маркетинга: Хорошо, давайте подумаем тогда, ну, с Яндексом в SEO особого смысла не имеет, потому что там все равно первая вся страница- это рекламная, и там без нее никуда не деться. Нерекламной выдачи практически нет на первой странице. Как быть, собственно, SEO интереснее больше в плане Google, потому что сейчас в России рекламы нет, Рекламироваться мы не можем.\n\n[14:52] Руководитель отдела маркетинга: Выдачи мы вроде бы на первых страницах есть, но тоже я не знаю, насколько этому можно доверять и верить. Даже из режима инкогнито я смотрю, но смотреть все равно с компьютера, с одной сети, мне кажется, это уже не сильно информативно и не сильно честно.\n\n[15:16] Руководитель отдела маркетинга: Поэтому, наверное, SEO больше на Google нам стоит затащивать. Если мы с этим можем как-то поработать с Tilda и Tilda, мы менять точно не будем.\n\n[15:28] Анастасия: Вот тут, Анастасия, собственно, два момента подчеркну, даже три момента подчеркну. Один очень технический, вот по поводу того, что с инкогнито, на самом деле, ваши опасения в целом верны. Есть полное ощущение, что периодически нет-нет, да и инкогнито тоже любит вопросы, ну, запросы подсобрать. Ну, то есть я иногда там с инкогнито могу зайти, куда-то ткнуть, и он мне показывает перечень запросов, которые были вбиты мною до этого.\n\n[15:54] Анастасия: Соответственно, это уже априори не очень инкогнито получается, и, да, эксперимент такой. Ну, то есть позиции надо проверять там через сервисы, если этим прям плотно заниматься. Это технический момент. Теперь про... Да, комментарий небольшой по поводу Яндекса. Тут чуть-чуть я с вами поспорю. На первой странице все-таки хотя бы треть выдачи- это органика.\n\n[16:16] Анастасия: Если мы говорим про... про такой, про запущенный случай. А если мы говорим конкретно про вашу нишу, там, ну, не 10 из 10 занято место, там было то ли по 3, сверху, снизу, то ли по 4, вот я сейчас не помню по памяти, но, соответственно, больше трети- это все равно органическая выдача, все равно, соответственно, вот это поисковое аранжирование важно и эффективно, тут против статистики, на самом деле, никак не попрешь.\n\n[16:43] Анастасия: Фишка всеошная в том, что Как бы постепенно, так или иначе, стоимость льда все равно снижается. Это на примере того же Яндекса тоже видно. И теперь, собственно, да, самый важный момент. Если коллеги скажут, что все-таки в данном случае, да, не такая высокая конкуренция, и в данном случае можно попробовать поработать, несмотря на то, что это тильда, тогда мы возьмемся, тогда мы с вами будем это предельно подробно обсуждать.\n\n[17:12] Анастасия: Сейчас обещать на всякий случай не буду. Да, то есть в данном случае нужно будет у коллег уточнить, потому что, как я, собственно, успел сказать, да, вот, наверное, за последние там, ну, месяца четыре, по крайней мере, да, возможно, уже и больше, наверное, с нового года как будто мы к Тильде решили не притрагиваться. Вот. Насколько это распространяется на все ниши, пока не смогу сказать.\n\n[17:36] Анастасия: В общем, уточню. Ваш интерес по поводу того, что в первую очередь сосредоточиться на Гугле, услышал. Здесь как бы проблем нет. Это все реализуем. Это мы обсудим. Но сейчас на самом деле хотелось бы попробовать копнуть в сторону рекламы. Расскажете ли, насколько вы ею довольны, есть ли смысл попробовать нам какой-то аудит рекламных кампаний провести, и если какие-то зоны роста подчеркнем, найдем и так далее, то, в общем, обсуждать, как бы нам с вами повзаимодействовать.\n\n[18:10] Руководитель отдела маркетинга: Нет, давайте я рекламу трогать не буду. Я поменяла несколько подрядчиков, в текущем вполне себе... Вполне нормально работает, не больно. А вот по поводу темы у вас... Ну, либо какие-то еще, может быть, инструменты, подумайте.\n\n[18:29] Анастасия: Тут у нас, на самом деле, их осталось, если мы про лидер-генерацию, да, там, не про создание сайта, а вот что-то такое, их, да я бы сказал, полтора, на самом деле. Хотел сказать два, но как будто не совсем. Момент номер раз - это управление репутацией. но у вас в вашей нише просто специализированных каких-то сервисов глобально нет агрегаторов, да, в которых можно там оценки понаставить, а, соответственно, это история, которая плавающая.\n\n[19:00] Анастасия: Есть история с попаданием в нейросети, в нейроответы, да, но... Я пытаюсь вот корректно сформулировать, потому что у меня, если честно, по этому поводу только нецензурные выражения. Я как сторонник SEO, мне вот эти нейроответы не очень сильно нравятся как таковые.\n\n[19:20] Анастасия: В общем, там глобально суть в чем произошла. Поисковые системы за счет нулевой выдачи отобрали просто кусок посещаемости у всех сайтов. И эта посещаемость, она не перераспределяется. Она просто отваливается сразу на этапе прочтения нулевой выдачи в поисковой системе.\n\n[19:41] Анастасия: И, соответственно, ссылки на вас вот на данный момент, пока как статистики выявили, они работают слабовато. Ну, и ссылки я имею в виду...\n\n[19:51] Руководитель отдела маркетинга: Вы имеете в виду из ответов, да? Да-да-да. То есть человек почитал, ему Олеса там или какой-то подобный сервис отвечал, и он оттуда из ссылок не переходит уже из-за этого ответа.\n\n[20:05] Анастасия: Абсолютно верно. В подавляющем большинстве случаев именно так. Но\n\n[20:09] Руководитель отдела маркетинга: как-то повлиять на то, чтобы упоминание бренда было там.\n\n[20:16] Анастасия: Чтобы было упоминание бренда, да. И в данном случае просто мы с вами будем отслеживать вот эти чуть более эфемерные показатели с точки зрения видимости в нейроответах. Это в целом возможно. То есть в этой части поработать вполне можно. Если вот это надо обсудить, давайте это обсудим, опять же, с учетом того, что нет у меня полноценной уверенности, что на тильде мы возьмемся.\n\n[20:43] Анастасия: То есть здесь такая же история, что мы упремся в микроразметку. Возможно, здесь такая же история, что, возможно, какие-то там дополнительные блоки в закрытом коде не получится реализовать. Ну, и, соответственно, вот, в какую-то стену немного упрёмся, как я, собственно, уже сформулировал.\n\n[21:04] Анастасия: Но обсудить обсудим. Давайте я на всякий случай у вас узнаю, есть ли у вас приоритетные товары или они в целом все равны, скажем\n\n[21:15] Руководитель отдела маркетинга: так. Приоритетный у нас самый, наверное, подобой - это радиогиды. Это все, что касается экскурсии. Аудиогид - это продукция для музея, для торфеев, для автоматизации экскурсий.\n\n[21:38] Руководитель отдела маркетинга: На втором месте, пожалуй. То, что мы сейчас хотим продвигать более активно, это GPS-ки, синхронный перевод. Это такие продукты, которые пока в меньшей степени продвинутые, но они обновлены не так давно, и это мы хотим сейчас более активно выпить в рынках.\n\n[22:03] Анастасия: То есть на самом деле вот последние два в итоге сейчас становятся прям самыми приоритетными?\n\n[22:11] Руководитель отдела маркетинга: Нет, они не так, чтобы самые приоритетные, мы не ожидаем от них самую большую выручку, самые большие продажи, но сейчас они совсем То есть это очень низшие вещи, которые сейчас мало достаточно продаются.\n\n[22:29] Анастасия: Тут уточню, в части блогового раздела его вроде бы не было на сайте, я же правильно помню?\n\n[22:38] Руководитель отдела маркетинга: Ну, как таковых блогов смотреть, это у нас либо портфолио есть, либо у нас... Нет,\n\n[22:50] Анастасия: это я окно сжал на самом деле.\n\n[22:53] Руководитель отдела маркетинга: А в блоге о нас есть медиа, там мы статьи начали недавно делать.\n\n[23:00] Анастасия: Вот эти статьи нам как раз потребуются, то есть часть стандартируемости и так далее. В первую очередь как раз информационные статьи нам и нужны будут. То есть это как раз такая часть, за счет которой мы будем выезжать. Там, если кратко, в общем, наверное, самая фундаментальная штука в GeoDrop.io, что примерно...\n\n[23:22] Анастасия: Самое фундаментальное - это тот самый link building. Это, на самом деле, тоже про ссылочную массу и про как раз информационные материалы. И в данном случае получается так, что мы пишем по три... Ну, я не уверен, что три, но я так предполагаю, коллеги скажут там по три нормально. Допустим, по три флагманских, скажем так, статьи на наш сайт, и для каждой из этих трех еще по две, скажем так, под статьи, типа под темы мы пишем для того, чтобы размещать где-то на сторонних ресурсах, на сторонних площадках и заладно на нас.\n\n[23:58] Анастасия: для того, чтобы одна тема была в трех вариациях раскрыта еще более глубоко, подробно.\n\n[24:05] Руководитель отдела маркетинга: А у нас вы имеете в виду наш сайт, правильно?\n\n[24:08] Анастасия: Да-да-да. Вот, собственно, в основном это как раз так и происходит. В части, Анастасия, я тоже вот поинтересуюсь, важный момент, насколько вы готовы будете к этому, в части затрат, я так подозреваю, где-то в районе 100-110, наверное, эта история вся обойдется в месяц, я имею в виду.\n\n[24:31] Анастасия: Насколько к этим затратам в целом готовы?\n\n[24:34] Руководитель отдела маркетинга: Ну, это мне надо обсуждать. Это практически уже наш рекламный бюджет. В месяц, когда я знаю, вы тратите. То есть рекламный бюджет на Яндекс, ну, на поиск, стоил через 200 тысяч за 70 месяцев. Соответственно, 110 на силу, ну, есть, если нужно обосновывать, на самом деле.\n\n[25:01] Руководитель отдела маркетинга: Мы с вами когда ожидаем результат? Через сколько месяцев?\n\n[25:06] Анастасия: Опять же, что считать результатом? Если мы с вами говорим там про наличие цитируемости в нейроответах, а вот конкретно сейчас про эту часть мы говорим, то по-нормальному, по-хорошему, где-то на третий месяц уже появляться вы будете. А дальше это просто геометрическая прогрессия. То есть мы же там по 9 статей, в общем, каждый месяц делаем.\n\n[25:30] Анастасия: Соответственно, цитируемость, вот она на постоянной основе и растет. То есть в данном случае дальше уже эта история просто должна на постоянной основе крутиться, потому что Так или иначе, да, нейросети развиваются. Понятно, что поддерживать это нужно.\n\n[25:47] Руководитель отдела маркетинга: Ну, смотрите, меня, естественно, интересует снижение стерматевида и увеличение количества лидов.\n\n[25:56] Анастасия: Вот эта история скорее про SEO. Если вот про лиды все-таки, не про просто цитируемость и узнаваемость и упоминание бренда, а вот про лиды, это скорее к SEO.\n\n[26:07] Руководитель отдела маркетинга: Это все-таки... Ну, тут оба направления, естественно. Дело в том, что, с одной стороны, о нашей продукции далеко не все турфирмы и гиды и музеи знают, в принципе, да? То есть, если мы берем Москву, Питер, там, или несколько крупных городов, Казань. Да, здесь культура есть, да, такая.\n\n[26:32] Руководитель отдела маркетинга: Я, например, вот сейчас была в Великом Новгороде, Куча туристов и никого с Радио МГИДы. То есть мы были с Радио МГИДами, и еще одна группа с нашими конкурентами. Все. Это потому, что куча туристических групп с Радио МГИДами идет. Но они не используют ни громкоговорителей даже, ничего. Только группу ведет своим голосом.\n\n[26:53] Руководитель отдела маркетинга: И это довольно-таки тяжелая история. Они используют аудио в Радио МГИДе. То есть вот эти культуры, регионы, их тоже хочется показать, рассказать. Поэтому здесь, с одной стороны, важно, чтобы об этом говорилось, да, то есть какой-то...\n\n[27:13] Руководитель отдела маркетинга: Просто F3I у нас плохо срабатывает. Ну, вообще практически никакой. Поэтому сейчас пытаемся промо-страницы, там что-то делать. Посмотрим результат. Какие-то выставки и так далее. А вот, ну, как новое направление, рекомендация именно уже через искусственную интеллекцию.\n\n[27:40] Руководитель отдела маркетинга: Кстати, а с какими вы работаете? Или это работает на всех?\n\n[27:46] Анастасия: Да, ну плюс-минус.\n\n[27:47] Руководитель отдела маркетинга: То есть они сами смотрят на Россию?\n\n[27:51] Анастасия: Работаем, по большому счету, в любом случае, под всех, потому что, ну, это одна технология. Понятное дело, что там, скорее всего, внутряночка чуть-чуть может разниться у них, но не слишком глобально, потому что вряд ли прям какие-то суперотличительные какие-то алгоритмы кто-то смог придумать. Ну, или, по крайней мере, они не изучены, об этом никто не знает.\n\n[28:13] Анастасия: Вот, соответственно, под все нейросети, да. Отчитываться мы будем, скорее всего, не по всем, а там просто по нескольким флагманским, скажем так. Ну, просто потому что это дорого. В общем, сервисы для отслеживания запросов в нейросетях, они прямо сильно дорогие, поэтому просто выберем там, я не знаю, 3-4. И как-то так это, скорее всего, будет выглядеть.\n\n[28:38] Руководитель отдела маркетинга: Понятно.\n\n[28:39] Анастасия: Так, что у меня было еще из вопросов? Я хотел уточнить, уточнить, уточнить, уточнить. Да, я вот... Две вещи буквально. Во-первых, можете пару, троечку конкурентов назвать?\n\n[28:53] Руководитель отдела маркетинга: Ну, кстати, они у вас там были?\n\n[28:56] Анастасия: Были. Если они подходят, то хорошо, давайте.\n\n[28:59] Руководитель отдела маркетинга: Да, давайте. Вы откройте, я вам скажу, кто из них. Вот я вижу, например, Вот они. Радиогидшоп - это та же компания, что и Кроми. Вот она пониже, Радиогидшоп, а у них пониже есть еще Кроми. Это их основной сайт.\n\n[29:19] Руководитель отдела маркетинга: У них два сайта получаются сейчас.\n\n[29:21] Анастасия: То есть Кроми - это основной?\n\n[29:24] Руководитель отдела маркетинга: Ну, видимо, да. А Шоп - это, видимо, для чисто продаж такой. Поменьше сайт. Здесь только Радиогиды, насколько я вижу. Ну, я бы не сказала, что они действительно нам конкуренты, именно по объему продажи и аренды, но, тем не менее, конкуренты.\n\n[29:46] Руководитель отдела маркетинга: Радиогайд.ру - это как раз таки радиогайд.ру. Да, это тоже наша питерская компания, наши конкуренты. Что тут еще можно посмотреть? Рейтикис нынче стал действительно активировались они, да, это китайские радиопилы, они в прошлом году очень агрессивно активировались, несколько сайтов понаделали, рекламируются, может быть, это не единственный их сайт, я уверена, их очень много на маркетах на разных, в общем-то, тоже их можно назвать нашими конкурентами, но по цене и по качеству они, конечно, ну, по цене они Два раза дешевле, но по качеству сильно уступают, но тем не менее.\n\n[30:35] Руководитель отдела маркетинга: Такой простой продукт, с обначальной, да, он пользуется. Мне кажется, начал набирать популярность. А микрофон 78 и M22 - это маркетплейсы. На микрофон 78 и наше оборудование в том числе и есть, ну, то есть это перекупщик, да, это закупает оборудование, продает.\n\n[30:58] Руководитель отдела маркетинга: M22 скорее конкурент. Тоже marketplace разных-разных. Но там не только радиогидов 22. Там все подряд. Но вот самые, наверное, пожалуй, именно как сайты-производители - это Кроме и radio-guide.ru. Эти два, ну и рейтики, в смысле.\n\n[31:21] Руководитель отдела маркетинга: Пожалуй, три наших главных конкурента именно в плане радиогидов. Остальные, я так понимаю, просто продают что-то.\n\n[31:33] Анастасия: Да, это понятно. И расскажите, пожалуйста, какие-то сильные стороны, отличительные от конкурентов. Какой-то оффер может быть? Как отстраиваетесь?\n\n[31:46] Руководитель отдела маркетинга: Во-первых, мы российская компания, российское производство. Сейчас для тех, кто работает в России, это важно. Особенно если это какие-то государственные закупки, гранты, музеи, для них важно, чтобы производитель был российский. Дальше у нас, собственно, все инженеры здесь, в Петербурге, штаб-квартира, и это значит, что мы можем кастомизировать оборудование, приехать, сделать настройку под клинч, под какую-то выставку музей.\n\n[32:20] Руководитель отдела маркетинга: Например, с каким-то китайским оборудованием это вряд ли получится. Плюс у нас гарантия 2 года, средний срок службы 5 лет, оборудование, мы его ремонтируем сами же, да, то есть не нужно никуда далеко отправлять, в Петербурге, сами его обслуживаем полностью.\n\n[32:44] Руководитель отдела маркетинга: Обычно там максимум, что требуется, замена батареек уже после нескольких лет службы. То есть есть оборудование, которое по 10 лет работает, Да, и у нас, в отличие от конкурентов, у нас хорошие приложения, которые очень хорошо расширяют функционал.\n\n[33:08] Руководитель отдела маркетинга: То есть это GPS для экскурсий, например, водных или автобусных, лидер-гид для того, чтобы запускать треки через приложение на всю группу, то есть это обычно либо какие-то иммерсивные экскурсии, Что у нас с этим происходит?\n\n[33:31] Руководитель отдела маркетинга: Смотрю, вот у меня, к примеру, радио. Мои работы там повлияли, что ли? Ну, не так, пожалуйста.\n\n[33:39] Анастасия: Ну, как будто бы может быть.\n\n[33:43] Руководитель отдела маркетинга: Вот какая-то шапка у меня, ее нет.\n\n[33:46] Анастасия: Какая-то шапка. Может, на самом деле, это у меня чуть-чуть перекашивает, все-таки учитывая, что я не на весь экран. Может быть, это внутренняя история моя, а может, что-то где-то не совсем так. Ну,\n\n[34:00] Руководитель отдела маркетинга: это... Ну, это, может, с работы не все это влияет. Я не знаю, где, я стараюсь следить. Соответственно, наши кредиты в качестве высокое, чтобы оборудование было, собственно, наши мозги, чтобы квартира Россия, Все брендирования - это, пожалуй, то, что и у конкурентов есть, но, правда, не у всех.\n\n[34:34] Руководитель отдела маркетинга: Мы быстро отвечаем, в отличие от конкурентов. То есть я проводила такие цены у покупателя, у конкурентов там что-то как-то с временем отнимают, не очень. Не все цены хотят говорить. У нас они открыты.\n\n[34:56] Руководитель отдела маркетинга: Ну, то есть мы от тех цен, которые на сайте, только в минусы можем пойти, ну, для каких-то более крупных проектов. Корректируем, даем скидки, даем рассрочку при необходимости.\n\n[35:11] Анастасия: Ну, я, в общем-то, всё, и всё записал, всё, что хотел. Если вдруг ещё у нас в процессе обсуждения с коллегами вопросы будут ещё, разумеется, отпишусь, а так как будто бы вот.\n\n[35:23] Руководитель отдела маркетинга: Ну, смотрите, мы всё-таки больше B2B, то есть даже не смотря на то, что у нас есть частные гиды, которые покупают оборудование, они могут его покупать как физицы, но, тем не менее, они его используют для работы, поэтому... надо рассматривать продукт чистый.\n\n[35:42] Анастасия: Окей. Ну, получается, и SEO плюс Jio мы будем рассматривать. Ну, понятно, что если плюс, то там, скорее всего, уже суммы совсем вас напугают. Будем, в общем, по отдельности, скорее всего. Но если вдруг за, прошу прощения, если вдруг за SEO все-таки способны будем взяться, то тогда тогда лучше, конечно, ее обсуждать, потому что, по-любому, степень коммерциализации, скажем так, этого инструмента, она в любом случае значительно выше, поэтому так.\n\n[36:17] Анастасия: Там просто есть достаточно забавные кейсы у коллег, которые решили не скрывать абсолютно и показали, что там ноль целых, запятая там, блин, дай бог памяти, по-моему, 38 десятитысячных, что ли, процента был прирост трафика из нейросетей.\n\n[36:38] Анастасия: Ну, это смешно.\n\n[36:41] Руководитель отдела маркетинга: Нет, на самом деле, смотрите, возможно, с нейросетями эта история и нормальная. Все зависит от того, кто аудитория. Если смотреть статистику нашу, аудитория, на самом деле, взрослее, чем мы с вами даже. Чаще, ну, примерно чуть больше половины это женщины, потому что в туризме в культуре исторически больше работают женщины, и возраст, ну да, от 35 до 45 лет процентов 20, и большая аудитория уже от 45, даже от 55.\n\n[37:22] Руководитель отдела маркетинга: То есть это люди все-таки достаточно взрослые. Растения они пользуются, мне кажется, в меньшей степени. Ну,\n\n[37:51] Анастасия: вот, собственно, да, в том и суть, что как раз нейросети выглядит менее, в любом случае, презентабельно в данном случае. Вот, и менее перспективно, собственно. Ну, в общем-то, получается, что все. Здесь, Анастасия, все кратко. Если мы возьмемся, то около недели мы будем анализировать и так далее.\n\n[38:14] Анастасия: Там, плюс-минус, может, чуть-чуть задержимся.\n\n[38:17] Руководитель отдела маркетинга: Да. По коммерческому предложению, когда можно будет ожидать и что-то сходить?\n\n[38:21] Анастасия: Это вот я про него как раз. Мы анализируем, соответственно, посмотрим на конкурентов, на объемы там и так далее, прикинем какие-то прогнозы. Вот около недели. Если мне скажут, что не возьмемся, ну, я прям сегодня-завтра в этом сообщу. Вот как бы долго нам нечего будет обсуждать. Поэтому вот так. Ну, все честно, правильно.\n\n[38:43] Руководитель отдела маркетинга: Хорошо, Егор, спасибо.\n\n[38:46] Анастасия: Да.\n\n[38:47] Руководитель отдела маркетинга: Ну, собственно, жду от вас туда обратной связи.\n\n[38:49] Анастасия: Договорились, договорились. Тогда будем на связи. Если будут вопросы, напишу. Если вдруг у вас там тоже вопросы или дополнения, тоже пишите, не стесняйтесь. Хорошо. Буду в том же аккаунте, что, собственно, Аркадий. Я еще сегодня вам с него напишу. Ссылочку скину, например, на этот аудит.\n\n[39:07] Руководитель отдела маркетинга: Хорошо. Все, пока.\n\n[39:10] Анастасия: Тогда на связи.\n\n[39:11] Руководитель отдела маркетинга: Спасибо.\n\n[39:12] Анастасия: Хорошего дня. Спасибо за встречу.\n\n[39:13] Руководитель отдела маркетинга: Всего доброго. Спасибо.",
  "wazzup": [
    {
      "at": "2026-01-16T10:34:23+03:00",
      "author": "2532",
      "text": "Для бренда Акула (Acoola Team) был выбран новый ответственный user_2188 (Гордиенко Евгения)"
    },
    {
      "at": "2026-01-16T10:34:25+03:00",
      "author": "624",
      "text": "Заявка с сайта : 2026-01-16 10:32:22\nТелефон: 79052601972\nПочта: \nФИО: Анастасия\n\nКомментарии: Сайт: crystal-sound.com\nБюджет: 70\nСтраница заявки: https://acoola.team/projects/\n\nИсточник (utm_source): yandex_acoola\nКанал (utm_medium): cpc\nКампания (utm_campaign): kr_acoola_bitrix_msk_spb_poisk\nОбъявление (utm_content): ch_yandex_direct|cid_97188551|gid_5605405014|ad_1878676187702649584|ph_205605405014|crt_0|pst_premium|ps_3|srct_search|src_none|devt_desktop|ret_205605405014|geo_2|cf_0|int_|tgt_205605405014|add_no|dop_\nКлючевое слово (utm_term): ---autotargeting\n\nID сайта в Calltouch: 54916\nID "
    },
    {
      "at": "2026-01-16T11:04:04+03:00",
      "author": "2532",
      "text": "[URL=https://dc6.sherlock-report.at/r/d6e911f3-7bd4-4919-910d-a2b7a0509eaa-597e6a8e3c9c678aaa]https://dc6.sherlock-report.at/r/d6e911f3-7bd4-4919-910d-a2b7a0509eaa-597e6a8e3c9c678aaa[/URL] отчет "
    },
    {
      "at": "2026-01-19T12:28:58+03:00",
      "author": "2358",
      "text": "[img]https://static.wazzup24.com/images/bitrix/telegram.png[/img]&nbsp;  Телефон:\nАнастасия, здравствуйте)\nМы с вами в пятницу созванивались, на счет интеграции для вашего сайта.\n\nПодскажите пожалуйста, какая у вас 1С и какая версия ?"
    },
    {
      "at": "2026-01-19T12:31:30+03:00",
      "author": "2358",
      "text": "[img]https://static.wazzup24.com/images/bitrix/telegram.png[/img]&nbsp;  crystal-sound.com:\nДобрый день. Самописная"
    },
    {
      "at": "2026-01-19T12:33:34+03:00",
      "author": "2358",
      "text": "[img]https://static.wazzup24.com/images/bitrix/telegram.png[/img]&nbsp;  Телефон:\nУ вас свой самописный склад ?"
    },
    {
      "at": "2026-01-19T12:34:08+03:00",
      "author": "2358",
      "text": "[img]https://static.wazzup24.com/images/bitrix/telegram.png[/img]&nbsp;  crystal-sound.com:\nну видимо да, в 1с все ведется"
    },
    {
      "at": "2026-01-19T12:37:15+03:00",
      "author": "2358",
      "text": "[img]https://static.wazzup24.com/images/bitrix/telegram.png[/img]&nbsp;  Телефон:\nА почему тогда самописный, если там все-таки 1с?\nКакая именно часть самописная?\n\nЭто важно, потому что Тильда умеет стандартными решениями интегрироваться, с самописными может не получится"
    },
    {
      "at": "2026-01-19T12:39:12+03:00",
      "author": "2358",
      "text": "[img]https://static.wazzup24.com/images/bitrix/telegram.png[/img]&nbsp;  crystal-sound.com:\nсклад полностью написан нашим программитом"
    },
    {
      "at": "2026-01-19T12:44:53+03:00",
      "author": "2358",
      "text": "[img]https://static.wazzup24.com/images/bitrix/telegram.png[/img]&nbsp;  Телефон:\nТак, а с 1С, что у вас тогда ?"
    },
    {
      "at": "2026-05-25T10:39:59+03:00",
      "author": "2812",
      "text": "[OPP-FIX-2026-05-25] OPPORTUNITY исправлен с 162,054,000 ₽ на 0 ₽. Причина: было = годовой оборот компании (UF_CRM_67B35193BAFB4), что искажало прогноз продаж. Новое значение = сумма productrows или 0."
    },
    {
      "at": "2026-06-09T09:43:21+03:00",
      "author": "2358",
      "text": "[img]https://static.wazzup24.com/images/bitrix/telegram.png[/img]&nbsp;  Аркадий Вострецов:\nАнастасия, добрый день! Это Аркадий, с Acoola Team, общались с вами насчёт продвижения! Не смог до вас дозвониться. Подскажите, пожалуйста, сегодня всё в силе? В 11:00 мск получится у вас ко встрече подключиться?"
    },
    {
      "at": "2026-06-09T09:44:21+03:00",
      "author": "2358",
      "text": "[img]https://static.wazzup24.com/images/bitrix/telegram.png[/img]&nbsp;  crystal-sound.com:\nДобрый день. Да, на пол часа, если только"
    },
    {
      "at": "2026-06-09T09:45:30+03:00",
      "author": "2358",
      "text": "[img]https://static.wazzup24.com/images/bitrix/telegram.png[/img]&nbsp;  Аркадий Вострецов:\nОтлично, этого времени вполне хватит! Как ссылка сформируется, вышлю вам сюда!"
    },
    {
      "at": "2026-06-09T09:45:38+03:00",
      "author": "2358",
      "text": "[img]https://static.wazzup24.com/images/bitrix/telegram.png[/img]&nbsp;  crystal-sound.com:\nок"
    },
    {
      "at": "2026-06-09T09:52:26+03:00",
      "author": "2358",
      "text": "[img]https://static.wazzup24.com/images/bitrix/telegram.png[/img]&nbsp;  Аркадий Вострецов:\nhttps://telemost.yandex.ru/j/74310472889904 - ссылка на встречу"
    },
    {
      "at": "2026-06-09T14:31:08+03:00",
      "author": "2358",
      "text": "[img]https://static.wazzup24.com/images/bitrix/telegram.png[/img]&nbsp;  Егор Семенихин:\nАнастасия, это Егор :f09f918b:\nТеперь на данном аккаунте буду орудовать я.\nЕщё раз благодарю за уделённое время!\n\nКратко изложу основные тезисы по итогам диалога:\n- Сайт на Tilda, переезд не планируется, поэтому SEO-возможности ограничены;\n- Основной фокус вам важен на Google, а не на Яндекс;\n- Есть потенциал по ссылочному профилю и индексации в Google;\n- Приоритетные направления - радиогиды, далее GPS-ки и синхронный перевод;\n- Важно учитывать B2B-аудиторию, а также российское происхождение компании и про"
    },
    {
      "at": "2026-06-09T14:38:18+03:00",
      "author": "2358",
      "text": "[img]https://static.wazzup24.com/images/bitrix/telegram.png[/img]&nbsp;  crystal-sound.com:\nготово"
    },
    {
      "at": "2026-06-09T14:48:13+03:00",
      "author": "2358",
      "text": "[img]https://static.wazzup24.com/images/bitrix/telegram.png[/img]&nbsp;  Егор Семенихин:\nЕсть контакт, благодарю!"
    },
    {
      "at": "2026-01-16T11:32:59+03:00",
      "author": "2532",
      "text": "24.02 - не актуально, других задач нет\n28.01 - недоступен\n27.01 - не отвечает\n22.01 - не отвечает\n16. 01 - запрос на интеграцию, сайт на тильде, срм битрикс, интеграция 1с и битрикс. с сайта попадают в битрикс, чтобы и в 1с попадали, и мы видили остатки в 1с.\n\nСео - в тильде, интернет магазин. \n\nДоговорились, что уточню по интеграции и свяжусь, в течении дня"
    },
    {
      "at": "2026-05-29T11:38:44+03:00",
      "author": "2832",
      "text": "29.05.26\n11:35, +7 905 260-19-72 - Анастасия (маркетолог): есть команда, с кем работают, основные задачи закрывают.. ОРИЕНТИРОВАЛ НА НЕЙРОНКИ, НА АУДИТ СОГЛАСНА! 09.06.26, 11:00 мск!!!\nИ, говорит, делается редизайн сайта сейчас, мелкие доработки!"
    },
    {
      "at": "2026-06-09T09:52:06+03:00",
      "author": "2832",
      "text": "[URL=https://telemost.yandex.ru/j/74310472889904]https://telemost.yandex.ru/j/74310472889904[/URL] - ссылка на встречу"
    }
  ],
  "brief_services": [
    9538
  ],
  "manager": "Семенихин Егор",
  "sfera": "Услуги для бизнеса"
}